lowmemorywordcount/README.MD
lowmemorywordcount/__init__.py
lowmemorywordcount/requirements.txt
lowmemorywordcount/thirdparty.json
lowmemorywordcount-0.10.dist-info/LICENSE.rst
lowmemorywordcount-0.10.dist-info/METADATA
lowmemorywordcount-0.10.dist-info/WHEEL
lowmemorywordcount-0.10.dist-info/top_level.txt
lowmemorywordcount-0.10.dist-info/RECORD
