Metadata-Version: 2.1
Name: lowmemorywordcount
Version: 0.10
Summary: Fast count of the occurrences of words in a text file or a given string - low memory consumption
Home-page: https://github.com/hansalemaos/lowmemorywordcount
Author: Johannes Fischer
Author-email: aulasparticularesdealemaosp@gmail.com
License: MIT
Keywords: word,count,nlp
Classifier: Development Status :: 4 - Beta
Classifier: Programming Language :: Python :: 3 :: Only
Classifier: Programming Language :: Python :: 3.10
Classifier: Topic :: Software Development :: Libraries :: Python Modules
Classifier: Topic :: Utilities
License-File: LICENSE.rst
Requires-Dist: regex
